printipy/__init__.py
printipy/api.py
printipy/data_objects.py
printipy/exceptions.py
printipy-1.2.1.dist-info/LICENSE
printipy-1.2.1.dist-info/METADATA
printipy-1.2.1.dist-info/WHEEL
printipy-1.2.1.dist-info/top_level.txt
printipy-1.2.1.dist-info/RECORD
