Metadata-Version: 2.1
Name: printipy
Version: 1.2.1
Summary: Printify API for Python
Home-page: https://github.com/lawrencemq/printipy
Author: Lawrence Weikum
Keywords: printify,print on demand,api
Classifier: Programming Language :: Python :: 3
Classifier: Programming Language :: Python :: 3.8
Classifier: Programming Language :: Python :: 3.9
Classifier: Programming Language :: Python :: 3.10
Classifier: Programming Language :: Python :: 3.11
Classifier: Programming Language :: Python :: 3.12
Classifier: Topic :: Internet
Classifier: License :: OSI Approved :: MIT License
Classifier: Operating System :: OS Independent
Requires-Python: >=3.8
License-File: LICENSE
Requires-Dist: requests
Requires-Dist: dataclasses-json
